{
  "lineChart": [
    {
      "name": "Mon",
      "uv": 4000,
      "pv": 2400
    },
    {
      "name": "Tues",
      "uv": 3000,
      "pv": 1398
    },
    {
      "name": "Wed",
      "uv": 2000,
      "pv": 9800
    },
    {
      "name": "Thurs",
      "uv": 2780,
      "pv": 3908
    },
    {
      "name": "Frid",
      "uv": 1890,
      "pv": 4800
    },
    {
      "name": "Satur",
      "uv": 2390,
      "pv": 3800
    },
    {
      "name": "Sun",
      "uv": 3490,
      "pv": 4300
    }
  ]
}
